awepatch/__init__.py
awepatch/_version.py
awepatch/utils.py
awepatch-0.0.14.dist-info/METADATA
awepatch-0.0.14.dist-info/WHEEL
awepatch-0.0.14.dist-info/licenses/LICENSE
awepatch-0.0.14.dist-info/RECORD
